quack/__init__.py
quack/activation.py
quack/autotuner.py
quack/broadcast_utils.py
quack/compile_utils.py
quack/copy_utils.py
quack/cross_entropy.py
quack/cute_dsl_ptxas.py
quack/cute_dsl_utils.py
quack/fast_math.py
quack/gemm.py
quack/gemm_act.py
quack/gemm_config.py
quack/gemm_dact.py
quack/gemm_default_epi.py
quack/gemm_interface.py
quack/gemm_sm100.py
quack/gemm_sm90.py
quack/gemm_symmetric.py
quack/gemm_wrapper_utils.py
quack/layout_utils.py
quack/linear.py
quack/linear_cross_entropy.py
quack/mlp.py
quack/pipeline.py
quack/reduce.py
quack/reduction_base.py
quack/rmsnorm.py
quack/sm100_utils.py
quack/sm90_utils.py
quack/softmax.py
quack/tensormap_manager.py
quack/tile_scheduler.py
quack/topk.py
quack/utils.py
quack/varlen_utils.py
quack/sort/bitonic_sort.py
quack/sort/generate_sorting_networks.py
quack/sort/sorting_networks.py
quack/sort/utils.py
quack_kernels-0.2.5.dist-info/licenses/LICENSE
quack_kernels-0.2.5.dist-info/METADATA
quack_kernels-0.2.5.dist-info/WHEEL
quack_kernels-0.2.5.dist-info/top_level.txt
quack_kernels-0.2.5.dist-info/RECORD
