Metadata-Version: 2.4
Name: quack-kernels
Version: 0.2.5
Requires-Python: >=3.10
License-File: LICENSE
Requires-Dist: nvidia-cutlass-dsl>=4.4.0.dev0
Requires-Dist: torch
Requires-Dist: apache-tvm-ffi<0.2,>=0.1.6
Requires-Dist: torch-c-dlpack-ext
Provides-Extra: dev
Requires-Dist: pre-commit; extra == "dev"
Requires-Dist: ruff; extra == "dev"
Dynamic: license-file
